KIG2013_G9_cpptopython.cp313-win_amd64.pyd
KIG2013_G9_cpptopython-0.2.3.dist-info/LICENSE
KIG2013_G9_cpptopython-0.2.3.dist-info/METADATA
KIG2013_G9_cpptopython-0.2.3.dist-info/WHEEL
KIG2013_G9_cpptopython-0.2.3.dist-info/top_level.txt
KIG2013_G9_cpptopython-0.2.3.dist-info/RECORD
